triton_metal
