Metadata-Version: 2.4
Name: triton-metal
Version: 3.3.0rc1
Summary: Enhanced Triton with Metal backend for Apple Silicon GPUs
Home-page: https://github.com/chengxingqiang/triton-metal/
Author: Cheng Xingqiang
Author-email: Cheng Xingqiang <chenxingqiang@turingai.cc>
License-Expression: MIT
Project-URL: Homepage, https://github.com/chengxingqiang/triton-metal
Project-URL: Bug Tracker, https://github.com/chengxingqiang/triton-metal/issues
Project-URL: Documentation, https://chenxingqiang.github.io/triton-metal/
Project-URL: Source Code, https://github.com/chengxingqiang/triton-metal
Keywords: deep learning,compiler,metal,apple silicon,m3,gpu,mlx
Classifier: Development Status :: 4 - Beta
Classifier: Intended Audience :: Developers
Classifier: Programming Language :: Python :: 3
Classifier: Programming Language :: Python :: 3.9
Classifier: Programming Language :: Python :: 3.10
Classifier: Programming Language :: Python :: 3.11
Classifier: Programming Language :: Python :: 3.12
Classifier: Programming Language :: Python :: 3.13
Classifier: Topic :: Scientific/Engineering :: Artificial Intelligence
Classifier: Operating System :: MacOS :: MacOS X
Classifier: Operating System :: POSIX :: Linux
Requires-Python: >=3.9,<3.14
License-File: LICENSE
License-File: LICENSE.metal
Requires-Dist: setuptools>=40.8.0
Requires-Dist: importlib-metadata; python_version < "3.10"
Provides-Extra: build
Requires-Dist: cmake>=3.20; extra == "build"
Requires-Dist: lit; extra == "build"
Provides-Extra: tests
Requires-Dist: autopep8; extra == "tests"
Requires-Dist: isort; extra == "tests"
Requires-Dist: numpy; extra == "tests"
Requires-Dist: pytest; extra == "tests"
Requires-Dist: pytest-forked; extra == "tests"
Requires-Dist: pytest-xdist; extra == "tests"
Requires-Dist: scipy>=1.7.1; extra == "tests"
Requires-Dist: llnl-hatchet; extra == "tests"
Provides-Extra: tutorials
Requires-Dist: matplotlib; extra == "tutorials"
Requires-Dist: pandas; extra == "tutorials"
Requires-Dist: tabulate; extra == "tutorials"
Provides-Extra: metal
Requires-Dist: mlx>=0.3.0; extra == "metal"
Dynamic: author
Dynamic: home-page
Dynamic: license-file
Dynamic: requires-python
